{"@type": "ElementFilterMembership", "@id": "String", "aliasIds": "List", "condition": "String", "declaredName": "String", "declaredShortName": "String", "documentation": "List", "elementId": "String", "isImplied": "String", "isImpliedIncluded": "String", "isLibraryElement": "String", "memberElement": "String", "memberElementId": "String", "memberName": "String", "memberShortName": "String", "membershipOwningNamespace": "String", "name": "String", "ownedAnnotation": "List", "ownedElement": "List", "ownedMemberElement": "String", "ownedMemberElementId": "String", "ownedMemberName": "String", "ownedMemberShortName": "String", "ownedRelatedElement": "List", "ownedRelationship": "List", "owner": "String", "owningMembership": "String", "owningNamespace": "String", "owningRelatedElement": "String", "owningRelationship": "String", "qualifiedName": "String", "relatedElement": "List", "shortName": "String", "source": "List", "target": "List", "textualRepresentation": "List", "visibility": "String"}